<xml xmlns="https://developers.google.com/blockly/xml"><block type="take_off_senior" id="AJ=;n;V1:i:7$4]ZW.V4" x="110" y="30"><next><block type="text_print" id="L~4$i]HQ[RD1`kCtuxSP"><value name="TEXT"><block type="text_join" id="LD{xrKL4r!up):4`HyVX"><mutation items="6"></mutation><value name="ADD0"><block type="text" id="xJ=w+jzgcJj!)ev0k4}v"><field name="TEXT">x:</field></block></value><value name="ADD1"><block type="get_pos_senior" id="1U)pL8wBC.ju)|QZpIRN"><field name="TYPE">x</field><field name="UNIT">in</field></block></value><value name="ADD2"><block type="text" id="]R`1y3GE48Lg2vZIb9B3"><field name="TEXT">y:</field></block></value><value name="ADD3"><block type="get_pos_senior" id="/R8a6Xon}-.m9U}3xA*L"><field name="TYPE">y</field><field name="UNIT">in</field></block></value><value name="ADD4"><block type="text" id="nLtCUCojr]jp6}9Xiuog"><field name="TEXT">z:</field></block></value><value name="ADD5"><block type="get_pos_senior" id="R#%|;=.O,WMCmOnbXhhq"><field name="TYPE">z</field><field name="UNIT">in</field></block></value></block></value><next><block type="move_senior" id="+N5`7k/|`@M#I9aH^$f6"><value name="ROLL"><shadow type="only_integers_limit_100" id="qV7;/#E5,Y7xn?^?~`.:"><field name="NUM">10</field></shadow></value><value name="PITCH"><shadow type="only_integers_limit_100" id="J5!W|x-X8a+PwMS_8Tu!"><field name="NUM">0</field></shadow></value><value name="YAW"><shadow type="only_integers_limit_100" id=",:4TwKH(k`!~MN)al;oT"><field name="NUM">0</field></shadow></value><value name="THROTTLE"><shadow type="only_integers_limit_100" id="E,KnGw2caHU1?heB!9,}"><field name="NUM">0</field></shadow></value><value name="NUM0"><shadow type="limit_0_To_100_decimal" id="F]Jh:.xrF!Ld%11A{u*E"><field name="NUM">2</field></shadow></value><next><block type="text_print" id="+^JwhAVHdFE@w-|pRbc9"><value name="TEXT"><block type="get_pos_senior" id=".qV}ykYQL_eSyg=4bkKw"><field name="TYPE">x</field><field name="UNIT">in</field></block></value><next><block type="move_senior" id="g_t`ti+QBt~(p)+USLL["><value name="ROLL"><shadow type="only_integers_limit_100" id="Kc$Uq0wVDW,n2oubfChy"><field name="NUM">0</field></shadow></value><value name="PITCH"><shadow type="only_integers_limit_100" id="%tUjtg2=E{wyY(Ou[hxA"><field name="NUM">10</field></shadow></value><value name="YAW"><shadow type="only_integers_limit_100" id="%RascXb5oNOhSL0-0y_n"><field name="NUM">0</field></shadow></value><value name="THROTTLE"><shadow type="only_integers_limit_100" id="}ymVgEz7R$KkCQ3Ud1DF"><field name="NUM">0</field></shadow></value><value name="NUM0"><shadow type="limit_0_To_100_decimal" id="34w}Ic-e7+)!7G`UyKdm"><field name="NUM">2</field></shadow></value><next><block type="text_print" id="i*/FM(j%@w~BLA8N_9}2"><value name="TEXT"><block type="get_pos_senior" id="9vLg*g4YY(BJ|1W;QMmv"><field name="TYPE">y</field><field name="UNIT">in</field></block></value><next><block type="move_senior" id="2AG+z,(l-{(3VV9V[6;)"><value name="ROLL"><shadow type="only_integers_limit_100" id="=N7S7(`)Z*`#5#4!]rQA"><field name="NUM">0</field></shadow></value><value name="PITCH"><shadow type="only_integers_limit_100" id="@cXAn_/3nSs@OpS@WD[!"><field name="NUM">0</field></shadow></value><value name="YAW"><shadow type="only_integers_limit_100" id="[)Tyf/IF+Nc!3RvsWyzB"><field name="NUM">0</field></shadow></value><value name="THROTTLE"><shadow type="only_integers_limit_100" id="efFNdFzGJ%=a]kY1(T.W"><field name="NUM">10</field></shadow></value><value name="NUM0"><shadow type="limit_0_To_100_decimal" id="`LQx7)jBbsrp_xzlb5?X"><field name="NUM">2</field></shadow></value><next><block type="text_print" id="*sw*VqaU$*[}Rs!zK!yx"><value name="TEXT"><block type="get_pos_senior" id=".?H)`N-T^v%v@d;ZId2*"><field name="TYPE">z</field><field name="UNIT">in</field></block></value><next><block type="land_senior" id="knrL(1p~GxvjUqQ4b9hw"></block></next></block></next></block></next></block></next></block></next></block></next></block></next></block></next></block></xml>