<xml xmlns="https://developers.google.com/blockly/xml"><block type="takeoff" id="4+_[}[9hkwP~DjghD(RU" x="70" y="30"><next><block type="go_position" id="];1[z_MO_gX,T5S.fVx+"><value name="NUM0"><shadow type="math_number" id="nK3ra%iH|/x3D_O@R?NX"><field name="NUM">0.5</field></shadow></value><value name="NUM1"><shadow type="math_number" id="WZhU{9e]cMRj#+?zSnoq"><field name="NUM">0</field></shadow></value><value name="NUM2"><shadow type="math_number" id="Guk}k^WIOq*6N}yexKDv"><field name="NUM">0.8</field></shadow></value><next><block type="wait" id="i|Of%QJL1zEt)zuuL6|B"><value name="NUM0"><shadow type="math_number" id="STs+rahBT$CI1cgw/.Pf"><field name="NUM">0.5</field></shadow></value><next><block type="go_position" id="#S_%S=S]T]jz@J9lWr^b"><value name="NUM0"><shadow type="math_number" id="kT?[nK+5u3SnekyWyoYu"><field name="NUM">0</field></shadow></value><value name="NUM1"><shadow type="math_number" id="Ffw!OvG9iBSYP=``_dA*"><field name="NUM">0.5</field></shadow></value><value name="NUM2"><shadow type="math_number" id="hTPjrqjCULn),:]c`kTJ"><field name="NUM">1.2</field></shadow></value><next><block type="wait" id="!,ESRGjvyfncdV,QwZ4w"><value name="NUM0"><shadow type="math_number" id="vP*^$IjgRL(B|L8+T_lR"><field name="NUM">0.5</field></shadow></value><next><block type="land" id=":,C5+@hjO@ZkOHkjFixh"></block></next></block></next></block></next></block></next></block></next></block></xml>