<xml xmlns="https://developers.google.com/blockly/xml"><block type="take_off_junior" id="%e`]lxy=z`I*pyji)1Lx" x="50" y="170"><next><block type="turn_power_junior" id="Lh!,G55n~RZ`~h[C]+.M"><field name="TYPE">Direction.LEFT</field><value name="SECONDS"><shadow type="math_number" id="i%sc-_A3==k=J7?:jz3N"><field name="NUM">3</field></shadow></value><value name="POWER"><shadow type="limit_0_To_100_50" id="U=OQ)H5d+Z1Z{p;(pIV`"><field name="NUM">40</field></shadow></value><next><block type="turn_power_junior" id="9y9LvF~J]q|dd7_QCS-`"><field name="TYPE">Direction.RIGHT</field><value name="SECONDS"><shadow type="math_number" id="Qp#u{%S@i6$_3`TOm_$+"><field name="NUM">1</field></shadow></value><value name="POWER"><shadow type="limit_0_To_100_50" id="h?#}cf-`UP/xXSy=0``@"><field name="NUM">80</field></shadow></value><next><block type="land_junior" id="-Ji2V[7Yg.dBFp7Ncc1u"></block></next></block></next></block></next></block></xml>